xavdid/__init__.py
xavdid-1.0.0.dist-info/entry_points.txt
xavdid-1.0.0.dist-info/WHEEL
xavdid-1.0.0.dist-info/METADATA
xavdid-1.0.0.dist-info/RECORD
